adif_merge/__init__.py
adif_merge-1.1.2.dist-info/LICENSE
adif_merge-1.1.2.dist-info/METADATA
adif_merge-1.1.2.dist-info/WHEEL
adif_merge-1.1.2.dist-info/entry_points.txt
adif_merge-1.1.2.dist-info/top_level.txt
adif_merge-1.1.2.dist-info/RECORD
