Metadata-Version: 2.1
Name: adif-merge
Version: 1.1.2
Summary: Amateur Radio ADIF compatible log file merge and resolution
Home-page: https://github.com/pleasantone/adif_merge
Author: Paul Traina
Author-email: bulk+pypi@pst.org
License: UNKNOWN
Platform: UNKNOWN
Classifier: Programming Language :: Python :: 3
Classifier: License :: OSI Approved :: GNU Affero General Public License v3 or later (AGPLv3+)
Classifier: Operating System :: OS Independent
Classifier: Development Status :: 4 - Beta
Classifier: Environment :: Console
Requires-Python: >=3.6
Requires-Dist: adif-io
